{
  "mpi_base": {
    "1": 0.2297,
    "2": 0.1307,
    "3": 0.174,
    "4": 0.1487,
    "5": 0.1246,
    "6": 0.11,
    "7": 0.1012,
    "8": 0.0926,
    "9": 0.0878,
    "10": 0.0821,
    "11": 0.083,
    "12": 0.0744,
    "13": 0.1062,
    "14": 0.1299,
    "15": 0.1341,
    "16": 0.1401
  },
  "omp_base": {
    "1": 0.2312,
    "2": 0.1312,
    "3": 0.1276,
    "4": 0.1055,
    "5": 0.0931,
    "6": 0.084,
    "7": 0.0741,
    "8": 0.0661,
    "9": 0.0609,
    "10": 0.0543,
    "11": 0.0518,
    "12": 0.0483,
    "13": 0.054,
    "14": 0.0691,
    "15": 0.0664,
    "16": 0.0668
  },
  "mpi_1c": {
    "1": 0.277,
    "2": 0.1565,
    "3": 0.2231,
    "4": 0.1969,
    "5": 0.1988,
    "6": 0.204,
    "7": 0.2199,
    "8": 0.1956,
    "9": 0.2298,
    "10": 0.213,
    "11": 0.256,
    "12": 0.2553,
    "13": 0.4014,
    "14": 0.7175,
    "15": 0.7189,
    "16": 0.7342
  },
  "omp_3b": {
    "1": 0.2464,
    "2": 0.2042,
    "3": 0.2287,
    "4": 0.1895,
    "5": 0.168,
    "6": 0.164,
    "7": 0.1512,
    "8": 0.1536,
    "9": 0.1511,
    "10": 0.1448,
    "11": 0.1353,
    "12": 0.1352,
    "13": 0.2037,
    "14": 0.2905,
    "15": 0.2732,
    "16": 0.2498
  }
}
